custom_terminal/__init__.py
custom_terminal/main.py
custom_terminal/commands/__init__.py
custom_terminal/commands/base_commands.py
custom_terminal/commands/weather.py
custom_terminal-0.1.7.dist-info/METADATA
custom_terminal-0.1.7.dist-info/WHEEL
custom_terminal-0.1.7.dist-info/entry_points.txt
custom_terminal-0.1.7.dist-info/top_level.txt
custom_terminal-0.1.7.dist-info/RECORD
