Metadata-Version: 2.4
Name: custom-terminal
Version: 0.1.7
Summary: A custom terminal with weather commands
Home-page: https://github.com/HarmandeepSinghDhillon/Custom-terminal
Author: Harmandeep Singh
Author-email: haricomputer4216@gmail.com
Classifier: Programming Language :: Python :: 3
Classifier: License :: OSI Approved :: MIT License
Classifier: Operating System :: OS Independent
Requires-Python: >=3.6
Requires-Dist: requests
Dynamic: author
Dynamic: author-email
Dynamic: classifier
Dynamic: description
Dynamic: description-content-type
Dynamic: home-page
Dynamic: requires-dist
Dynamic: requires-python
Dynamic: summary
